welcom.py
hello_pypi_test_chedan20260113-0.1.0.dist-info/METADATA
hello_pypi_test_chedan20260113-0.1.0.dist-info/WHEEL
hello_pypi_test_chedan20260113-0.1.0.dist-info/top_level.txt
hello_pypi_test_chedan20260113-0.1.0.dist-info/RECORD
