Metadata-Version: 2.4
Name: hello_pypi_test_chedan20260113
Version: 0.1.0
Summary: 一个用于测试上传流程的简单包
Author-email: YourName <your@email.com>
Project-URL: Homepage, https://github.com/yourname/test-repo
Requires-Python: >=3.7
